[
    {
        "test_score_gib": 0.9390452525918602,
        "train_score": 0.9417095754965076,
        "test_score": 0.9390452525918602,
        "num_samples": 19022,
        "fit_time": 1068,
        "score_time": 285,
        "time": 1353,
        "parameters": {
            "boosting_type": "gbdt",
            "colsample_bytree": 0.7,
            "learning_rate": 0.05,
            "min_child_samples": 20,
            "min_child_weight": 0.001,
            "min_split_gain": 0.0,
            "n_estimators": 100,
            "num_leaves": 31,
            "reg_alpha": 0.0,
            "reg_lambda": 0.0
        },
        "done_at": 1772786240121,
        "split_id": 0,
        "best_iteration_": 100
    },
    {
        "test_score_gib": 0.9423774365777671,
        "train_score": 0.9411764929861315,
        "test_score": 0.9423774365777671,
        "num_samples": 19022,
        "fit_time": 1398,
        "score_time": 228,
        "time": 1626,
        "parameters": {
            "boosting_type": "gbdt",
            "colsample_bytree": 0.7,
            "learning_rate": 0.05,
            "min_child_samples": 20,
            "min_child_weight": 0.001,
            "min_split_gain": 0.0,
            "n_estimators": 100,
            "num_leaves": 31,
            "reg_alpha": 0.0,
            "reg_lambda": 0.0
        },
        "done_at": 1772786240396,
        "split_id": 1,
        "best_iteration_": 100
    },
    {
        "test_score_gib": 0.9402186893079703,
        "train_score": 0.9418243228136385,
        "test_score": 0.9402186893079703,
        "num_samples": 19022,
        "fit_time": 1402,
        "score_time": 247,
        "time": 1649,
        "parameters": {
            "boosting_type": "gbdt",
            "colsample_bytree": 0.7,
            "learning_rate": 0.05,
            "min_child_samples": 20,
            "min_child_weight": 0.001,
            "min_split_gain": 0.0,
            "n_estimators": 100,
            "num_leaves": 31,
            "reg_alpha": 0.0,
            "reg_lambda": 0.0
        },
        "done_at": 1772786240419,
        "split_id": 2,
        "best_iteration_": 100
    },
    {
        "test_score_gib": 0.9368668942739312,
        "train_score": 0.9424218282498176,
        "test_score": 0.9368668942739312,
        "num_samples": 19021,
        "fit_time": 1421,
        "score_time": 231,
        "time": 1652,
        "parameters": {
            "boosting_type": "gbdt",
            "colsample_bytree": 0.7,
            "learning_rate": 0.05,
            "min_child_samples": 20,
            "min_child_weight": 0.001,
            "min_split_gain": 0.0,
            "n_estimators": 100,
            "num_leaves": 31,
            "reg_alpha": 0.0,
            "reg_lambda": 0.0
        },
        "done_at": 1772786240423,
        "split_id": 3,
        "best_iteration_": 100
    },
    {
        "test_score_gib": 0.9381383263311144,
        "train_score": 0.9421839719085661,
        "test_score": 0.9381383263311144,
        "num_samples": 19021,
        "fit_time": 933,
        "score_time": 229,
        "time": 1162,
        "parameters": {
            "boosting_type": "gbdt",
            "colsample_bytree": 0.7,
            "learning_rate": 0.05,
            "min_child_samples": 20,
            "min_child_weight": 0.001,
            "min_split_gain": 0.0,
            "n_estimators": 100,
            "num_leaves": 31,
            "reg_alpha": 0.0,
            "reg_lambda": 0.0
        },
        "done_at": 1772786241290,
        "split_id": 4,
        "best_iteration_": 100
    },
    {
        "test_score_gib": 0.9388840514943168,
        "train_score": 0.9417671389821407,
        "test_score": 0.9388840514943168,
        "num_samples": 19022,
        "fit_time": 1010,
        "score_time": 240,
        "time": 1250,
        "parameters": {
            "boosting_type": "gbdt",
            "colsample_bytree": 0.9,
            "learning_rate": 0.05,
            "min_child_samples": 20,
            "min_child_weight": 0.001,
            "min_split_gain": 0.0,
            "n_estimators": 100,
            "num_leaves": 31,
            "reg_alpha": 0.0,
            "reg_lambda": 0.0
        },
        "done_at": 1772786241649,
        "split_id": 0,
        "best_iteration_": 100
    },
    {
        "test_score_gib": 0.9423862991156136,
        "train_score": 0.9412759172255379,
        "test_score": 0.9423862991156136,
        "num_samples": 19022,
        "fit_time": 1157,
        "score_time": 206,
        "time": 1363,
        "parameters": {
            "boosting_type": "gbdt",
            "colsample_bytree": 0.9,
            "learning_rate": 0.05,
            "min_child_samples": 20,
            "min_child_weight": 0.001,
            "min_split_gain": 0.0,
            "n_estimators": 100,
            "num_leaves": 31,
            "reg_alpha": 0.0,
            "reg_lambda": 0.0
        },
        "done_at": 1772786241786,
        "split_id": 1,
        "best_iteration_": 100
    },
    {
        "test_score_gib": 0.9404300759321166,
        "train_score": 0.9418751609445833,
        "test_score": 0.9404300759321166,
        "num_samples": 19022,
        "fit_time": 1113,
        "score_time": 196,
        "time": 1309,
        "parameters": {
            "boosting_type": "gbdt",
            "colsample_bytree": 0.9,
            "learning_rate": 0.05,
            "min_child_samples": 20,
            "min_child_weight": 0.001,
            "min_split_gain": 0.0,
            "n_estimators": 100,
            "num_leaves": 31,
            "reg_alpha": 0.0,
            "reg_lambda": 0.0
        },
        "done_at": 1772786241736,
        "split_id": 2,
        "best_iteration_": 100
    },
    {
        "test_score_gib": 0.9367146673114697,
        "train_score": 0.9426846473974714,
        "test_score": 0.9367146673114697,
        "num_samples": 19021,
        "fit_time": 780,
        "score_time": 159,
        "time": 939,
        "parameters": {
            "boosting_type": "gbdt",
            "colsample_bytree": 0.9,
            "learning_rate": 0.05,
            "min_child_samples": 20,
            "min_child_weight": 0.001,
            "min_split_gain": 0.0,
            "n_estimators": 100,
            "num_leaves": 31,
            "reg_alpha": 0.0,
            "reg_lambda": 0.0
        },
        "done_at": 1772786242233,
        "split_id": 3,
        "best_iteration_": 100
    },
    {
        "test_score_gib": 0.9382065307622768,
        "train_score": 0.9422954108828727,
        "test_score": 0.9382065307622768,
        "num_samples": 19021,
        "fit_time": 673,
        "score_time": 140,
        "time": 813,
        "parameters": {
            "boosting_type": "gbdt",
            "colsample_bytree": 0.9,
            "learning_rate": 0.05,
            "min_child_samples": 20,
            "min_child_weight": 0.001,
            "min_split_gain": 0.0,
            "n_estimators": 100,
            "num_leaves": 31,
            "reg_alpha": 0.0,
            "reg_lambda": 0.0
        },
        "done_at": 1772786242464,
        "split_id": 4,
        "best_iteration_": 100
    }
]