{
    "modelInputNRows": 95108,
    "modelInputNCols": 140,
    "modelInputIsSparse": true,
    "modelInputMemory": 34619316,
    "usedGridSearch": true,
    "gridSize": 2,
    "gridBestScore": 0.9428707563027197,
    "gridCells": [
        {
            "params": {
                "boosting_type": "gbdt",
                "colsample_bytree": 0.7,
                "learning_rate": 0.05,
                "min_child_samples": 31,
                "min_child_weight": 0.001,
                "min_split_gain": 0.0,
                "n_estimators": 102,
                "num_leaves": 31,
                "reg_alpha": 0.0,
                "reg_lambda": 0.0
            },
            "score": 0.9428707563027197,
            "scoreStd": 0.0010893402144682577,
            "fitTime": 4.1166,
            "fitTimeStd": 1.4790616755226942,
            "scoreTime": 0.4496,
            "scoreTimeStd": 0.080728185908021
        },
        {
            "params": {
                "boosting_type": "gbdt",
                "colsample_bytree": 0.9,
                "learning_rate": 0.05,
                "min_child_samples": 31,
                "min_child_weight": 0.001,
                "min_split_gain": 0.0,
                "n_estimators": 102,
                "num_leaves": 31,
                "reg_alpha": 0.0,
                "reg_lambda": 0.0
            },
            "score": 0.9428298271733943,
            "scoreStd": 0.0011802435327702614,
            "fitTime": 3.1792,
            "fitTimeStd": 0.9216223521594948,
            "scoreTime": 0.30619999999999997,
            "scoreTimeStd": 0.07979824559474975
        }
    ],
    "rawImportance": {
        "variables": [
            "needs_parking",
            "adults",
            "room_changed",
            "total_nights",
            "lead_time",
            "company_booking",
            "has_children",
            "has_waiting_list",
            "is_repeated_guest",
            "adr",
            "weekend_flag",
            "arrival_date_week_number",
            "arrival_month_num",
            "dummy:agent_group:other_agent",
            "dummy:agent_group:agent_9",
            "dummy:agent_group:no_agent",
            "dummy:agent_group:agent_240",
            "dummy:agent_group:agent_1",
            "dummy:agent_group:agent_14",
            "dummy:agent_group:agent_7",
            "dummy:agent_group:agent_6",
            "dummy:customer_type:Transient",
            "dummy:customer_type:Transient-Party",
            "dummy:customer_type:Contract",
            "dummy:booking_changes_group:0_change",
            "dummy:booking_changes_group:1_change",
            "dummy:booking_changes_group:2+_change",
            "dummy:market_segment:Online TA",
            "dummy:market_segment:Offline TA/TO",
            "dummy:market_segment:Groups",
            "dummy:market_segment:Direct",
            "dummy:market_segment:Corporate",
            "dummy:market_segment:Aviation",
            "dummy:country_group:PRT",
            "dummy:country_group:Other",
            "dummy:country_group:GBR",
            "dummy:country_group:FRA",
            "dummy:country_group:ESP",
            "dummy:country_group:DEU",
            "dummy:country_group:IRL",
            "dummy:country_group:BRA",
            "dummy:country_group:NLD",
            "dummy:country_group:SWE",
            "dummy:country_group:POL",
            "dummy:previous_cancellation_group:no_previous",
            "dummy:previous_cancellation_group:one_previous",
            "dummy:stay_type:2_3_nights",
            "dummy:stay_type:4_7_nights",
            "dummy:stay_type:1_night",
            "dummy:stay_type:8plus_nights",
            "dummy:reserved_room_type:A",
            "dummy:reserved_room_type:D",
            "dummy:reserved_room_type:E",
            "dummy:reserved_room_type:F",
            "dummy:reserved_room_type:B",
            "dummy:trip_type:mixed_trip",
            "dummy:trip_type:business_trip",
            "dummy:guest_group:couple",
            "dummy:guest_group:single",
            "dummy:hotel:City Hotel",
            "dummy:hotel:Resort Hotel",
            "dummy:season:3_summer",
            "dummy:season:2_spring",
            "dummy:season:4_autumn",
            "dummy:season:1_winter",
            "dummy:assigned_room_type:A",
            "dummy:assigned_room_type:D",
            "dummy:assigned_room_type:F",
            "dummy:assigned_room_type:C",
            "dummy:assigned_room_type:B",
            "dummy:deposit_type:No Deposit",
            "dummy:deposit_type:Non Refund",
            "dummy:deposit_type:Refundable",
            "dummy:meal:BB",
            "dummy:meal:HB",
            "dummy:meal:SC",
            "dummy:meal:Undefined",
            "dummy:meal:FB",
            "dummy:distribution_channel:TA/TO",
            "dummy:distribution_channel:Direct",
            "dummy:distribution_channel:Corporate",
            "dummy:distribution_channel:GDS",
            "dummy:special_requests_group:0_request",
            "dummy:special_requests_group:1_request",
            "dummy:special_requests_group:2_requests",
            "dummy:special_requests_group:3_requests",
            "dummy:special_requests_group:4+_requests"
        ],
        "importances": [
            0.058736182474096246,
            0.00047920476026028257,
            0.06007881183552704,
            0.00925854613337568,
            0.07539290683936621,
            0.0007902251399866423,
            0.00100765429997891,
            0.0018309552468542493,
            0.006232682776486646,
            0.011678474012002605,
            0.0004963322111425817,
            0.007158251150909779,
            0.0014979456996371402,
            0.03050564619442051,
            0.030214609233539497,
            0.001985373075214676,
            0.019065371959393233,
            0.0010138300211687409,
            0.0035779981745205493,
            0.016213446269125305,
            0.0004164975779585343,
            0.018405579324089462,
            0.013733776020486853,
            0.0032341354418391646,
            0.010841285024702841,
            0.004624189821196697,
            0.00028246184205520217,
            0.07234825618181441,
            0.0013293528895392478,
            0.003066754632519231,
            0.0046415858334625994,
            0.0012239832513979856,
            0.00010468636704125322,
            0.0733478446181823,
            0.004014112000814402,
            0.005095373773446741,
            0.004217536661744657,
            0.003573179994644533,
            0.006958782357001099,
            0.0008259195707546498,
            0.001079548578997451,
            0.000860029100469198,
            7.504935796204543e-05,
            2.082247691434562e-05,
            0.020634577521592614,
            0.013318704536348702,
            0.0005133832256306044,
            0.00012509582908160297,
            0.0009295569326833685,
            0.00018281921120745674,
            0.001135745562086038,
            5.0717687372112736e-05,
            2.496310172734802e-05,
            3.0414620998544936e-05,
            0.00014075417234110605,
            0.0003230738655653549,
            5.072776656747849e-05,
            0.001181333123727345,
            0.0011618166963682209,
            0.002270940128158748,
            0.0014837811914766318,
            0.0018818200185914246,
            0.00010376755278356953,
            0.00010662673445737707,
            0.000618754435058019,
            0.0030245078349088123,
            0.00016353585837692927,
            8.422587002605248e-05,
            0.00036182758048742967,
            0.0009674211349015978,
            0.11752173906234818,
            0.17885440512772785,
            0.0010716561546757813,
            0.0018329226843233058,
            0.0019263732271451593,
            0.000361911334157886,
            0.0017080855820463701,
            9.518164088179377e-05,
            0.010767330018248132,
            0.0039248486997081385,
            0.0006890236222939821,
            0.00045004332171496637,
            0.034719295995937816,
            0.011104400006010802,
            0.007453738218821674,
            0.004144428346390006,
            0.000968534559002245
        ]
    },
    "probaAware": true
}